randomify/__init__.py
randomify/main.py
randomify-0.11.dist-info/LICENSE
randomify-0.11.dist-info/METADATA
randomify-0.11.dist-info/WHEEL
randomify-0.11.dist-info/top_level.txt
randomify-0.11.dist-info/RECORD
